{
  "segments": [
    {
      "text": "We are given three functions: f1, f2, f3.",
      "start_char": 0,
      "end_char": 41,
      "label": "empty",
      "label_info": {
        "type": "empty"
      }
    },
    {
      "text": "Let's break down the expression:\n   f3(f2(f1('bcksrut', 'q'))) Step 1: Compute f1('bcksrut', 'q')\n   f1(text, value) does:\n        text_list = list(text)  -> ['b','c','k','s','r','u','t']\n        text_list.append(value) -> appends 'q' -> ['b','c','k','s','r','u','t','q']\n        returns ''.join(...) -> 'bcksrutq'\n\n Step 2: Compute f2 on the result of f1, i.e., f2('bcksrutq')\n   f2(s) returns ''.join([c for c in s if c.isspace()])",
      "start_char": 44,
      "end_char": 479,
      "label": "mental_execution",
      "label_info": {
        "type": "mental_execution"
      }
    },
    {
      "text": "The string 'bcksrutq' has no space characters. So the list comprehension will be empty.",
      "start_char": 483,
      "end_char": 570,
      "label": "mental_execution",
      "label_info": {
        "type": "mental_execution"
      }
    },
    {
      "text": "Therefore, f2('bcksrutq') returns an empty string: ''\n\n Step 3: Compute f3 on the result of f2, i.e., f3('')\n   f3(text) does:\n        for c in text: ... but text is empty, so the loop doesn't run. then it returns bool(text) -> bool('') is False.",
      "start_char": 574,
      "end_char": 828,
      "label": "mental_execution",
      "label_info": {
        "type": "mental_execution"
      }
    },
    {
      "text": "Therefore, the entire expression f3(f2(f1('bcksrut', 'q'))) returns False.",
      "start_char": 831,
      "end_char": 905,
      "label": "mental_execution",
      "label_info": {
        "type": "mental_execution"
      }
    },
    {
      "text": "However, note that the function f3 is defined to return a boolean, and the assert statement is comparing to that boolean. But the problem says: \"complete the assert statement with the output when executing the code on the given test case\"\n\n We are to output the value that would make the assert statement true?",
      "start_char": 908,
      "end_char": 1218,
      "label": "code_analysis",
      "label_info": {
        "type": "code_analysis"
      }
    },
    {
      "text": "Actually, the problem says: \n \"Only return the output of the function without any other information and assert statement.\" But note: the expression is f3(...)",
      "start_char": 1221,
      "end_char": 1379,
      "label": "code_analysis",
      "label_info": {
        "type": "code_analysis"
      }
    },
    {
      "text": "and we found it returns False.",
      "start_char": 1382,
      "end_char": 1412,
      "label": "mental_execution",
      "label_info": {
        "type": "mental_execution"
      }
    },
    {
      "text": "However, let me double-check the functions:\n\n   f1: appends a character and returns the string. Correct.",
      "start_char": 1415,
      "end_char": 1519,
      "label": "code_analysis",
      "label_info": {
        "type": "code_analysis"
      }
    },
    {
      "text": "f2: returns a string of all the whitespace characters in s. Since there are none, it returns empty string.",
      "start_char": 1524,
      "end_char": 1630,
      "label": "mental_execution",
      "label_info": {
        "type": "mental_execution"
      }
    },
    {
      "text": "f3: \n        for c in text: ...",
      "start_char": 1635,
      "end_char": 1666,
      "label": "code_analysis",
      "label_info": {
        "type": "code_analysis"
      }
    },
    {
      "text": "if it finds any non-numeric character, returns False.",
      "start_char": 1667,
      "end_char": 1720,
      "label": "code_analysis",
      "label_info": {
        "type": "code_analysis"
      }
    },
    {
      "text": "If the loop completes (meaning all are numeric) then it returns bool(text) (which is False for empty string, True for non-empty).",
      "start_char": 1730,
      "end_char": 1859,
      "label": "code_analysis",
      "label_info": {
        "type": "code_analysis"
      }
    },
    {
      "text": "In our case, the input to f3 is the empty string. The loop doesn't run, so we return bool('') -> False. So the result is False. But note: the problem says \"If the output is a string, enclose it in single quotes.\"",
      "start_char": 1869,
      "end_char": 2081,
      "label": "mental_execution",
      "label_info": {
        "type": "mental_execution"
      }
    },
    {
      "text": "However, the output here is a boolean (False). So we just write False.",
      "start_char": 2088,
      "end_char": 2158,
      "label": "mental_execution",
      "label_info": {
        "type": "mental_execution"
      }
    },
    {
      "text": "However, let me check the function f3: \n   It returns either False (if a non-numeric is found) or bool(text) (if all are numeric). For an empty string, the loop doesn't run and returns bool('') -> False.",
      "start_char": 2161,
      "end_char": 2368,
      "label": "code_analysis",
      "label_info": {
        "type": "code_analysis"
      }
    },
    {
      "text": "Therefore, the output is False. But wait: what if the empty string is considered?",
      "start_char": 2371,
      "end_char": 2452,
      "label": "mental_execution",
      "label_info": {
        "type": "mental_execution"
      }
    },
    {
      "text": "The function f3 returns False for the empty string. So the answer is False.",
      "start_char": 2455,
      "end_char": 2530,
      "label": "mental_execution",
      "label_info": {
        "type": "mental_execution"
      }
    },
    {
      "text": "However, note that the problem says: \"complete the assert statement\".",
      "start_char": 2535,
      "end_char": 2604,
      "label": "code_analysis",
      "label_info": {
        "type": "code_analysis"
      }
    },
    {
      "text": "The assert statement is:\n\n   assert f3(f2(f1('bcksrut', 'q'))) == \n\n We are to fill in the right-hand side. We found it is False. But note: the problem says \"Only return the output of the function without any other information and assert statement.",
      "start_char": 2605,
      "end_char": 2853,
      "label": "code_analysis",
      "label_info": {
        "type": "code_analysis"
      }
    },
    {
      "text": "\"\n\n So we just output: False\n\n However, let me re-read: \"which may contain errors\" \u2014 but in this case, the functions are defined and the test case runs without error.",
      "start_char": 2855,
      "end_char": 3021,
      "label": "mental_execution",
      "label_info": {
        "type": "mental_execution"
      }
    },
    {
      "text": "Therefore, the answer is False.",
      "start_char": 3024,
      "end_char": 3055,
      "label": "empty",
      "label_info": {
        "type": "empty"
      }
    }
  ],
  "original_reasoning": "We are given three functions: f1, f2, f3.\n\n Let's break down the expression:\n   f3(f2(f1('bcksrut', 'q')))\n\n Step 1: Compute f1('bcksrut', 'q')\n   f1(text, value) does:\n        text_list = list(text)  -> ['b','c','k','s','r','u','t']\n        text_list.append(value) -> appends 'q' -> ['b','c','k','s','r','u','t','q']\n        returns ''.join(...) -> 'bcksrutq'\n\n Step 2: Compute f2 on the result of f1, i.e., f2('bcksrutq')\n   f2(s) returns ''.join([c for c in s if c.isspace()])\n   The string 'bcksrutq' has no space characters. So the list comprehension will be empty.\n   Therefore, f2('bcksrutq') returns an empty string: ''\n\n Step 3: Compute f3 on the result of f2, i.e., f3('')\n   f3(text) does:\n        for c in text: ... but text is empty, so the loop doesn't run.\n        then it returns bool(text) -> bool('') is False.\n\n Therefore, the entire expression f3(f2(f1('bcksrut', 'q'))) returns False.\n\n However, note that the function f3 is defined to return a boolean, and the assert statement is comparing to that boolean.\n\n But the problem says: \"complete the assert statement with the output when executing the code on the given test case\"\n\n We are to output the value that would make the assert statement true? Actually, the problem says: \n \"Only return the output of the function without any other information and assert statement.\"\n\n But note: the expression is f3(...) and we found it returns False.\n\n However, let me double-check the functions:\n\n   f1: appends a character and returns the string. Correct.\n\n   f2: returns a string of all the whitespace characters in s. Since there are none, it returns empty string.\n\n   f3: \n        for c in text: ... if it finds any non-numeric character, returns False. \n        If the loop completes (meaning all are numeric) then it returns bool(text) (which is False for empty string, True for non-empty).\n\n        In our case, the input to f3 is the empty string. The loop doesn't run, so we return bool('') -> False.\n\n So the result is False.\n\n But note: the problem says \"If the output is a string, enclose it in single quotes.\" \n However, the output here is a boolean (False). So we just write False.\n\n However, let me check the function f3: \n   It returns either False (if a non-numeric is found) or bool(text) (if all are numeric). \n   For an empty string, the loop doesn't run and returns bool('') -> False.\n\n Therefore, the output is False.\n\n But wait: what if the empty string is considered? The function f3 returns False for the empty string.\n\n So the answer is False.\n\n However, note that the problem says: \"complete the assert statement\". The assert statement is:\n\n   assert f3(f2(f1('bcksrut', 'q'))) == \n\n We are to fill in the right-hand side. We found it is False.\n\n But note: the problem says \"Only return the output of the function without any other information and assert statement.\"\n\n So we just output: False\n\n However, let me re-read: \"which may contain errors\" \u2014 but in this case, the functions are defined and the test case runs without error.\n\n Therefore, the answer is False."
}